ShenjingwangluoYuShenduXuexiJiangyiFudanQiuxipeng/README.md
ShenjingwangluoYuShenduXuexiJiangyiFudanQiuxipeng/__init__.py
ShenjingwangluoYuShenduXuexiJiangyiFudanQiuxipeng/__main__.py
ShenjingwangluoYuShenduXuexiJiangyiFudanQiuxipeng/file.pdf
ShenjingwangluoYuShenduXuexiJiangyiFudanQiuxipeng/index.html
shenjingwangluo_yu_shendu_xuexi_jiangyi_fudan_qiuxipeng-2024.3.2.0.dist-info/METADATA
shenjingwangluo_yu_shendu_xuexi_jiangyi_fudan_qiuxipeng-2024.3.2.0.dist-info/WHEEL
shenjingwangluo_yu_shendu_xuexi_jiangyi_fudan_qiuxipeng-2024.3.2.0.dist-info/entry_points.txt
shenjingwangluo_yu_shendu_xuexi_jiangyi_fudan_qiuxipeng-2024.3.2.0.dist-info/top_level.txt
shenjingwangluo_yu_shendu_xuexi_jiangyi_fudan_qiuxipeng-2024.3.2.0.dist-info/RECORD
